ssscoring/__init__.py
ssscoring/appcommon.py
ssscoring/calc.py
ssscoring/cli.py
ssscoring/constants.py
ssscoring/datatypes.py
ssscoring/errors.py
ssscoring/flysight.py
ssscoring/mapview.py
ssscoring/notebook.py
ssscoring/ssscoremoved.py
ssscoring/ssscoremultiple.py
ssscoring/resources/__init__.py
ssscoring/resources/drop-zones-loc-elev.csv
ssscoring/resources/instructions.md
ssscoring/resources/moved-2-new-domain.md
ssscoring-2.10.4.dist-info/licenses/LICENSE.txt
ssscoring-2.10.4.dist-info/METADATA
ssscoring-2.10.4.dist-info/WHEEL
ssscoring-2.10.4.dist-info/entry_points.txt
ssscoring-2.10.4.dist-info/top_level.txt
ssscoring-2.10.4.dist-info/RECORD
