Metadata-Version: 2.4
Name: ssscoring
Version: 2.10.4
Summary: ssscoring - Speed Skydiving scoring tools
Author-email: Eugene Ciurana pr3d4t0r <ssscoring.project@cime.net>
License-Expression: BSD-3-Clause
Classifier: Intended Audience :: Other Audience
Classifier: Operating System :: MacOS
Classifier: Operating System :: Unix
Classifier: Programming Language :: Python :: 3
Classifier: Programming Language :: Python :: 3.9
Requires-Python: >=3.9.9
License-File: LICENSE.txt
Requires-Dist: bokeh==2.4.3
Requires-Dist: click
Requires-Dist: geopy
Requires-Dist: haversine
Requires-Dist: importlib-resources
Requires-Dist: jupyter_bokeh==3.0.4
Requires-Dist: numpy<1.26.4
Requires-Dist: psutil
Requires-Dist: pydeck
Requires-Dist: streamlit==1.44.1
Dynamic: license-file
